example/__init__.py
example/admin.py
example/apps.py
example/models.py
example/tests.py
example/urls.py
example/views.py
example/migrations/0001_initial.py
example/migrations/__init__.py
like_system/__init__.py
like_system/admin.py
like_system/apps.py
like_system/conf.py
like_system/models.py
like_system/tests.py
like_system/urls.py
like_system/views.py
like_system/migrations/0001_initial.py
like_system/migrations/__init__.py
project/__init__.py
project/asgi.py
project/settings.py
project/urls.py
project/wsgi.py
django_like_systems-0.0.1.dist-info/LICENSE
django_like_systems-0.0.1.dist-info/METADATA
django_like_systems-0.0.1.dist-info/WHEEL
django_like_systems-0.0.1.dist-info/top_level.txt
django_like_systems-0.0.1.dist-info/RECORD
