Metadata-Version: 2.1
Name: django-like-systems
Version: 0.0.1
Summary: An easy way to add feedback'like/dislike' to any of your models.
Home-page: https://github.com/dcontm/django-like-system
Author: Dmitry Konstantinov
Author-email: dcontm@gmail.com
License: UNKNOWN
Platform: UNKNOWN
Classifier: Programming Language :: Python :: 3
Classifier: License :: OSI Approved :: MIT License
Classifier: Operating System :: OS Independent
Classifier: Framework :: Django
Classifier: Framework :: Django :: 2.2
Classifier: Framework :: Django :: 3.0
Classifier: Programming Language :: Python
Classifier: Programming Language :: Python :: 3.6
Classifier: Programming Language :: Python :: 3.7
Classifier: Programming Language :: Python :: 3.8
Requires-Python: >=3.6
